{
    "P75a6d00": {
        "name": "Captain RN Walcott",
        "filename": "The_Steamer_Great_Western_small.jpg"
    },
    "P27e1de1": {
        "name": "Captain Superintendent RN Jackson",
        "filename": "The_Steamer_Great_Western_small.jpg"
    },
    "P583a060": {
        "name": "Robert Young",
        "filename": "The_Steamer_Great_Western_small.jpg"
    },
    "Pa175e89": {
        "name": "Robert Stephenson",
        "filename": "The_Steamer_Great_Western_small.jpg"
    },
    "P911e435": {
        "name": "Oliver Lang",
        "filename": "The_Steamer_Great_Western_small.jpg"
    },
    "P65d94d1": {
        "name": "William Edward Acraman",
        "filename": "The_Steamer_Great_Western_small.jpg"
    },
    "P486e13c": {
        "name": "William Bruce Adair",
        "filename": "The_Steamer_Great_Western_small.jpg"
    },
    "P5d75d26": {
        "name": "Thomas Baynton",
        "filename": "The_Steamer_Great_Western_small.jpg"
    },
    "P8cf4795": {
        "name": "Robert Bright",
        "filename": "The_Steamer_Great_Western_small.jpg"
    },
    "Pd2d070f": {
        "name": "Henry Bush",
        "filename": "The_Steamer_Great_Western_small.jpg"
    },
    "P0e07348": {
        "name": "W. H. Castle",
        "filename": "The_Steamer_Great_Western_small.jpg"
    },
    "P84f3a38": {
        "name": "J. B. Clarke",
        "filename": "The_Steamer_Great_Western_small.jpg"
    },
    "P0d85b8c": {
        "name": "Joseph Cookson",
        "filename": "The_Steamer_Great_Western_small.jpg"
    },
    "P3216ee0": {
        "name": "Thomas Cruttwell",
        "filename": "The_Steamer_Great_Western_small.jpg"
    },
    "P31d57a3": {
        "name": "James Cunningham",
        "filename": "The_Steamer_Great_Western_small.jpg"
    },
    "P07fc6fd": {
        "name": "Mr. Dowell",
        "filename": "The_Steamer_Great_Western_small.jpg"
    },
    "P64b599a": {
        "name": "F. H. Falkner",
        "filename": "The_Steamer_Great_Western_small.jpg"
    },
    "P27e393d": {
        "name": "Dr. Charles Fox",
        "filename": "The_Steamer_Great_Western_small.jpg"
    },
    "Pc92ab7a": {
        "name": "Charles Fripp",
        "filename": "The_Steamer_Great_Western_small.jpg"
    },
    "P7d1396d": {
        "name": "George Gibbs",
        "filename": "The_Steamer_Great_Western_small.jpg"
    },
    "P4549038": {
        "name": "Henry G. Godwin",
        "filename": "The_Steamer_Great_Western_small.jpg"
    },
    "Pde8bb3b": {
        "name": "Thomas Guppy",
        "filename": "The_Steamer_Great_Western_small.jpg"
    },
    "P614e508": {
        "name": "Samuel Hall",
        "filename": "The_Steamer_Great_Western_small.jpg"
    },
    "P0b09531": {
        "name": "John Hare",
        "filename": "The_Steamer_Great_Western_small.jpg"
    },
    "P213d362": {
        "name": "John Harford",
        "filename": "The_Steamer_Great_Western_small.jpg"
    },
    "P0bb2268": {
        "name": "Thomas Kingsbury",
        "filename": "The_Steamer_Great_Western_small.jpg"
    },
    "P5e0dcd5": {
        "name": "Thomas Kington",
        "filename": "The_Steamer_Great_Western_small.jpg"
    },
    "P5dbd5cf": {
        "name": "Mr. Levy",
        "filename": "The_Steamer_Great_Western_small.jpg"
    },
    "Paec4c00": {
        "name": "Miss. Lucas",
        "filename": "The_Steamer_Great_Western_small.jpg"
    },
    "P31f9551": {
        "name": "Samuel Lucas",
        "filename": "The_Steamer_Great_Western_small.jpg"
    },
    "P24c7bc8": {
        "name": "Peter Maze (the elder)",
        "filename": "The_Steamer_Great_Western_small.jpg"
    },
    "P0c43b52": {
        "name": "Missing",
        "filename": "The_Steamer_Great_Western_small.jpg"
    },
    "Pfcc95d4": {
        "name": "John Moxham",
        "filename": "The_Steamer_Great_Western_small.jpg"
    },
    "P4772ead": {
        "name": "John Edye",
        "filename": "The_Steamer_Great_Western_small.jpg"
    },
    "Pc36597f": {
        "name": "Mr. Harding",
        "filename": "The_Steamer_Great_Western_small.jpg"
    },
    "P0414806": {
        "name": "Thomas Pycroft",
        "filename": "The_Steamer_Great_Western_small.jpg"
    },
    "P81d7cee": {
        "name": "Richard Robinson",
        "filename": "The_Steamer_Great_Western_small.jpg"
    },
    "P731164e": {
        "name": "Robert Scott",
        "filename": "The_Steamer_Great_Western_small.jpg"
    },
    "Pcc26502": {
        "name": "John Stafford",
        "filename": "The_Steamer_Great_Western_small.jpg"
    },
    "Pca95c87": {
        "name": "John Taylor",
        "filename": "The_Steamer_Great_Western_small.jpg"
    },
    "P7ed7235": {
        "name": "Rev. Taylor",
        "filename": "The_Steamer_Great_Western_small.jpg"
    },
    "Pdf636ea": {
        "name": "John Vining",
        "filename": "The_Steamer_Great_Western_small.jpg"
    },
    "P8153936": {
        "name": "Mr. Warr",
        "filename": "The_Steamer_Great_Western_small.jpg"
    },
    "P11ef2c1": {
        "name": "Thomas Boneville Were",
        "filename": "The_Steamer_Great_Western_small.jpg"
    },
    "P63b6944": {
        "name": "John Winwood",
        "filename": "The_Steamer_Great_Western_small.jpg"
    },
    "Pcdb002d": {
        "name": "George Lunnell",
        "filename": "The_Steamer_Great_Western_small.jpg"
    },
    "Pc7065c8": {
        "name": "Robert Stepehnson",
        "filename": "The_Steamer_Great_Western_small.jpg"
    },
    "P35fe10a": {
        "name": "William Symonds",
        "filename": "The_Steamer_Great_Western_small.jpg"
    },
    "P5f5f012": {
        "name": "Thomas Kington Bayly",
        "filename": "The_Steamer_Great_Western_small.jpg"
    },
    "P7642cdb": {
        "name": "William Claxton",
        "filename": "The_Steamer_Great_Western_small.jpg"
    },
    "P1facb30": {
        "name": "Captain Crozier",
        "filename": "The_Steamer_Great_Western_small.jpg"
    },
    "P61487dd": {
        "name": "Mr. Stedder",
        "filename": "The_Steamer_Great_Western_small.jpg"
    },
    "Pbdae1a4": {
        "name": "Mr. Smith",
        "filename": "The_Steamer_Great_Western_small.jpg"
    },
    "P6f40b22": {
        "name": "Francis Humphrys",
        "filename": "The_Steamer_Great_Western_small.jpg"
    },
    "Paec9448": {
        "name": "J. Bates",
        "filename": "The_Steamer_Great_Western_small.jpg"
    },
    "Pdcca239": {
        "name": "G. Norman",
        "filename": "The_Steamer_Great_Western_small.jpg"
    },
    "Pdf419e2": {
        "name": "W. Morgan",
        "filename": "The_Steamer_Great_Western_small.jpg"
    },
    "P52a93b9": {
        "name": "J. P. Bartrun",
        "filename": "The_Steamer_Great_Western_small.jpg"
    },
    "P0a2aaca": {
        "name": "A. P. Johnson",
        "filename": "The_Steamer_Great_Western_small.jpg"
    },
    "P255b842": {
        "name": "John Grantham",
        "filename": "The_Steamer_Great_Western_small.jpg"
    },
    "Pa41a4bb": {
        "name": "Bryan Donkin",
        "filename": "The_Steamer_Great_Western_small.jpg"
    },
    "Pe8c03f7": {
        "name": "William Edward Parry",
        "filename": "The_Steamer_Great_Western_small.jpg"
    },
    "P2db0a91": {
        "name": "Francis Petit Smith",
        "filename": "The_Steamer_Great_Western_small.jpg"
    },
    "P396149c": {
        "name": "Captain Ed R. N. Chappel",
        "filename": "The_Steamer_Great_Western_small.jpg"
    },
    "P0fbe946": {
        "name": "George Rennie",
        "filename": "The_Steamer_Great_Western_small.jpg"
    },
    "Pcde88e8": {
        "name": "John Barnes",
        "filename": "The_Steamer_Great_Western_small.jpg"
    },
    "P7f5bcfb": {
        "name": "John William Miles",
        "filename": "The_Steamer_Great_Western_small.jpg"
    },
    "P1b769d8": {
        "name": "John Barrow",
        "filename": "The_Steamer_Great_Western_small.jpg"
    },
    "P34b9c04": {
        "name": "W. Hamilton",
        "filename": "The_Steamer_Great_Western_small.jpg"
    },
    "P003735b": {
        "name": "Coalbrookdale Foundry",
        "filename": "The_Steamer_Great_Western_small.jpg"
    },
    "Pb7959b5": {
        "name": "E. E. Allen",
        "filename": "The_Steamer_Great_Western_small.jpg"
    },
    "P924d3a5": {
        "name": "J. Abernathy",
        "filename": "The_Steamer_Great_Western_small.jpg"
    },
    "P1f9a356": {
        "name": "G. B. Airey",
        "filename": "The_Steamer_Great_Western_small.jpg"
    },
    "Pe6b31b1": {
        "name": "Mr. Andrews",
        "filename": "The_Steamer_Great_Western_small.jpg"
    },
    "P5bb5593": {
        "name": "J. Appold",
        "filename": "The_Steamer_Great_Western_small.jpg"
    },
    "P22c1700": {
        "name": "W. G. Armstrong",
        "filename": "The_Steamer_Great_Western_small.jpg"
    },
    "P2a4d50c": {
        "name": "Henry Bach",
        "filename": "The_Steamer_Great_Western_small.jpg"
    },
    "P45fa4df": {
        "name": "C. Birch Bagster",
        "filename": "The_Steamer_Great_Western_small.jpg"
    },
    "P907549a": {
        "name": "S. Baker",
        "filename": "The_Steamer_Great_Western_small.jpg"
    },
    "Peff1ecf": {
        "name": "William Barber",
        "filename": "The_Steamer_Great_Western_small.jpg"
    },
    "P95343c8": {
        "name": "Thomas Bazley",
        "filename": "The_Steamer_Great_Western_small.jpg"
    },
    "P70ee733": {
        "name": "Samuel Beale",
        "filename": "The_Steamer_Great_Western_small.jpg"
    },
    "Pa9f16bc": {
        "name": "W. Beardmore",
        "filename": "The_Steamer_Great_Western_small.jpg"
    },
    "Pa9188c5": {
        "name": "C. A. Beaumont",
        "filename": "The_Steamer_Great_Western_small.jpg"
    },
    "Pa0fad1a": {
        "name": "Mr. Beckwith",
        "filename": "The_Steamer_Great_Western_small.jpg"
    },
    "Padb462d": {
        "name": "Mr. Bedford",
        "filename": "The_Steamer_Great_Western_small.jpg"
    },
    "P2d079d5": {
        "name": "RN Captain Beecher",
        "filename": "The_Steamer_Great_Western_small.jpg"
    },
    "Pd8d0be5": {
        "name": "Thomas Stirling Begbie",
        "filename": "The_Steamer_Great_Western_small.jpg"
    },
    "P9318229": {
        "name": "A. W. Bell",
        "filename": "The_Steamer_Great_Western_small.jpg"
    },
    "Pe722bad": {
        "name": "F. Henry F. Berkeley",
        "filename": "The_Steamer_Great_Western_small.jpg"
    },
    "Pf976e95": {
        "name": "Rev. E. L. Berthon",
        "filename": "The_Steamer_Great_Western_small.jpg"
    },
    "P65dddc1": {
        "name": "E. L. Betts",
        "filename": "The_Steamer_Great_Western_small.jpg"
    },
    "Pb8f82db": {
        "name": "Charles Bidfield",
        "filename": "The_Steamer_Great_Western_small.jpg"
    },
    "P70c67c4": {
        "name": "Thomas E. Blackwell",
        "filename": "The_Steamer_Great_Western_small.jpg"
    },
    "Pf473900": {
        "name": "Henry Wollaston Blake",
        "filename": "The_Steamer_Great_Western_small.jpg"
    },
    "P9305cf9": {
        "name": "Thomas Bold",
        "filename": "The_Steamer_Great_Western_small.jpg"
    },
    "Pf8c2104": {
        "name": "Charles J. Boulton",
        "filename": "The_Steamer_Great_Western_small.jpg"
    },
    "P6806b64": {
        "name": "George Bower",
        "filename": "The_Steamer_Great_Western_small.jpg"
    },
    "P8ccc02d": {
        "name": "Bowling Iron Co",
        "filename": "The_Steamer_Great_Western_small.jpg"
    },
    "P557f57b": {
        "name": "Edwin Boyle",
        "filename": "The_Steamer_Great_Western_small.jpg"
    },
    "P93bebe5": {
        "name": "James Braidwood",
        "filename": "The_Steamer_Great_Western_small.jpg"
    },
    "Pa38a678": {
        "name": "George Braine",
        "filename": "The_Steamer_Great_Western_small.jpg"
    },
    "Pb3faeb5": {
        "name": "R. P. Brereton",
        "filename": "The_Steamer_Great_Western_small.jpg"
    },
    "P10571c1": {
        "name": "Mr. Briscoe",
        "filename": "The_Steamer_Great_Western_small.jpg"
    },
    "P9288226": {
        "name": "British Plate Glass Co",
        "filename": "The_Steamer_Great_Western_small.jpg"
    },
    "P247977d": {
        "name": "Rowland Brotherhood",
        "filename": "The_Steamer_Great_Western_small.jpg"
    },
    "P58947a8": {
        "name": "James Brothers",
        "filename": "The_Steamer_Great_Western_small.jpg"
    },
    "Pf7cc06e": {
        "name": "Edward Brown Whitstone",
        "filename": "The_Steamer_Great_Western_small.jpg"
    },
    "P6b31a8a": {
        "name": "Frederick Brown",
        "filename": "The_Steamer_Great_Western_small.jpg"
    },
    "P5f3d76a": {
        "name": "Robert Brown",
        "filename": "The_Steamer_Great_Western_small.jpg"
    },
    "Pc2199f9": {
        "name": "C. D. Bruce",
        "filename": "The_Steamer_Great_Western_small.jpg"
    },
    "Pd2a9380": {
        "name": "Isambard Kingdom Brunel",
        "filename": "The_Steamer_Great_Western_small.jpg"
    },
    "P1712c2d": {
        "name": "George W. Bull",
        "filename": "The_Steamer_Great_Western_small.jpg"
    },
    "Pd2a1ef2": {
        "name": "Joseph Burch",
        "filename": "The_Steamer_Great_Western_small.jpg"
    },
    "Pdf43bdc": {
        "name": "F. George Burke",
        "filename": "The_Steamer_Great_Western_small.jpg"
    },
    "P3cb45a0": {
        "name": "Michael Burke",
        "filename": "The_Steamer_Great_Western_small.jpg"
    },
    "Pbbc152b": {
        "name": "Sir George Burke",
        "filename": "The_Steamer_Great_Western_small.jpg"
    },
    "P490d0e3": {
        "name": "E. W. Buscoe",
        "filename": "The_Steamer_Great_Western_small.jpg"
    },
    "Pec49f79": {
        "name": "C J Mare",
        "filename": "The_Steamer_Great_Western_small.jpg"
    },
    "Pd5917b7": {
        "name": "Mr. Caldwell",
        "filename": "The_Steamer_Great_Western_small.jpg"
    },
    "P93c8f46": {
        "name": "R. J. R. Campbell",
        "filename": "The_Steamer_Great_Western_small.jpg"
    },
    "Pd49ce9c": {
        "name": "R. I. R. Campbell",
        "filename": "The_Steamer_Great_Western_small.jpg"
    },
    "Pcb9f69c": {
        "name": "W. Carpmael",
        "filename": "The_Steamer_Great_Western_small.jpg"
    },
    "P948350a": {
        "name": "George Carter",
        "filename": "The_Steamer_Great_Western_small.jpg"
    },
    "Pdae8081": {
        "name": "Mr. Christie",
        "filename": "The_Steamer_Great_Western_small.jpg"
    },
    "P47a7e94": {
        "name": "John Clare",
        "filename": "The_Steamer_Great_Western_small.jpg"
    },
    "P51ef14c": {
        "name": "George Clark",
        "filename": "The_Steamer_Great_Western_small.jpg"
    },
    "Pf8778e5": {
        "name": "Latimer Clark",
        "filename": "The_Steamer_Great_Western_small.jpg"
    },
    "Pbcd9f80": {
        "name": "Seymour Clarke",
        "filename": "The_Steamer_Great_Western_small.jpg"
    },
    "P17b6189": {
        "name": "Christopher Claxton",
        "filename": "The_Steamer_Great_Western_small.jpg"
    },
    "P780e29b": {
        "name": "William Clay",
        "filename": "The_Steamer_Great_Western_small.jpg"
    },
    "Pa207179": {
        "name": "J. J. Clifton",
        "filename": "The_Steamer_Great_Western_small.jpg"
    },
    "Pa19c424": {
        "name": "Henry Colebrook",
        "filename": "The_Steamer_Great_Western_small.jpg"
    },
    "P7e8d125": {
        "name": "Mr. Coleman",
        "filename": "The_Steamer_Great_Western_small.jpg"
    },
    "P08d4e2d": {
        "name": "J. R. Conder",
        "filename": "The_Steamer_Great_Western_small.jpg"
    },
    "Pcf807c1": {
        "name": "John Coode",
        "filename": "The_Steamer_Great_Western_small.jpg"
    },
    "P774f372": {
        "name": "Mr. Cook",
        "filename": "The_Steamer_Great_Western_small.jpg"
    },
    "P2cc4695": {
        "name": "J. Cooke",
        "filename": "The_Steamer_Great_Western_small.jpg"
    },
    "P7d77c3f": {
        "name": "William Cory Jr",
        "filename": "The_Steamer_Great_Western_small.jpg"
    },
    "P74d080e": {
        "name": "J. Crace",
        "filename": "The_Steamer_Great_Western_small.jpg"
    },
    "P3114728": {
        "name": "Mr. Crace",
        "filename": "The_Steamer_Great_Western_small.jpg"
    },
    "Pcd6b6eb": {
        "name": "Robert Cumming",
        "filename": "The_Steamer_Great_Western_small.jpg"
    },
    "P11cc443": {
        "name": "N. W. Cummins",
        "filename": "The_Steamer_Great_Western_small.jpg"
    },
    "P97b1859": {
        "name": "Cunard Line",
        "filename": "The_Steamer_Great_Western_small.jpg"
    },
    "Pe810bf3": {
        "name": "Joseph Cundall",
        "filename": "The_Steamer_Great_Western_small.jpg"
    },
    "P68df043": {
        "name": "D Brown J Weir",
        "filename": "The_Steamer_Great_Western_small.jpg"
    },
    "Pec8e676": {
        "name": "Arthur J. Davey",
        "filename": "The_Steamer_Great_Western_small.jpg"
    },
    "P6d257d7": {
        "name": "Mr. Davis",
        "filename": "The_Steamer_Great_Western_small.jpg"
    },
    "Pa548255": {
        "name": "I. J. Delaney",
        "filename": "The_Steamer_Great_Western_small.jpg"
    },
    "P9ae2902": {
        "name": "William Y. Dent",
        "filename": "The_Steamer_Great_Western_small.jpg"
    },
    "Pe7fbcd5": {
        "name": "J. Derby",
        "filename": "The_Steamer_Great_Western_small.jpg"
    },
    "Pb2920cc": {
        "name": "John Dickson",
        "filename": "The_Steamer_Great_Western_small.jpg"
    },
    "P32ef41b": {
        "name": "Samuel Dinsmere",
        "filename": "The_Steamer_Great_Western_small.jpg"
    },
    "Pe52938b": {
        "name": "J. B. Dunn",
        "filename": "The_Steamer_Great_Western_small.jpg"
    },
    "P4d94549": {
        "name": "William Edye",
        "filename": "The_Steamer_Great_Western_small.jpg"
    },
    "P0cd1354": {
        "name": "RN Engledrew",
        "filename": "The_Steamer_Great_Western_small.jpg"
    },
    "Pbcde2c2": {
        "name": "William Essie",
        "filename": "The_Steamer_Great_Western_small.jpg"
    },
    "P1756032": {
        "name": "Frederick John Evans",
        "filename": "The_Steamer_Great_Western_small.jpg"
    },
    "Pa4146e7": {
        "name": "William Fairbairn",
        "filename": "The_Steamer_Great_Western_small.jpg"
    },
    "P61b2ba1": {
        "name": "R. I. Fayrer",
        "filename": "The_Steamer_Great_Western_small.jpg"
    },
    "Pb1f9db0": {
        "name": "Mr. Ferguson",
        "filename": "The_Steamer_Great_Western_small.jpg"
    },
    "P10d2271": {
        "name": "Joshua Field",
        "filename": "The_Steamer_Great_Western_small.jpg"
    },
    "Pcf0a201": {
        "name": "Edward Finch",
        "filename": "The_Steamer_Great_Western_small.jpg"
    },
    "P426b635": {
        "name": "Mr. Ford",
        "filename": "The_Steamer_Great_Western_small.jpg"
    },
    "P4a129f2": {
        "name": "John Fowler",
        "filename": "The_Steamer_Great_Western_small.jpg"
    },
    "P38b9294": {
        "name": "Mr. Fowler",
        "filename": "The_Steamer_Great_Western_small.jpg"
    },
    "P110295e": {
        "name": "R. W. Fox",
        "filename": "The_Steamer_Great_Western_small.jpg"
    },
    "P89c1ef7": {
        "name": "Fred Krupps Cast Steel Iron Works",
        "filename": "The_Steamer_Great_Western_small.jpg"
    },
    "P35ca7ff": {
        "name": "Joseph Freeman",
        "filename": "The_Steamer_Great_Western_small.jpg"
    },
    "P15abf9f": {
        "name": "Mr. French",
        "filename": "The_Steamer_Great_Western_small.jpg"
    },
    "Padbe721": {
        "name": "Charles Freshfield",
        "filename": "The_Steamer_Great_Western_small.jpg"
    },
    "P9666d78": {
        "name": "William Froude",
        "filename": "The_Steamer_Great_Western_small.jpg"
    },
    "Pb2b67a8": {
        "name": "Charles Geach",
        "filename": "The_Steamer_Great_Western_small.jpg"
    },
    "P7808c5e": {
        "name": "J. Gibson",
        "filename": "The_Steamer_Great_Western_small.jpg"
    },
    "P4053327": {
        "name": "Gladstone of Sir W Harris",
        "filename": "The_Steamer_Great_Western_small.jpg"
    },
    "Pd0d687a": {
        "name": "Daniel Gooch",
        "filename": "The_Steamer_Great_Western_small.jpg"
    },
    "P40f6a07": {
        "name": "Alexander Gordon",
        "filename": "The_Steamer_Great_Western_small.jpg"
    },
    "P67828ac": {
        "name": "John Grant",
        "filename": "The_Steamer_Great_Western_small.jpg"
    },
    "P781233e": {
        "name": "W. Green",
        "filename": "The_Steamer_Great_Western_small.jpg"
    },
    "Pa91ac13": {
        "name": "John Gregory",
        "filename": "The_Steamer_Great_Western_small.jpg"
    },
    "Pd37e184": {
        "name": "Robert Griffiths",
        "filename": "The_Steamer_Great_Western_small.jpg"
    },
    "P910953c": {
        "name": "Mr. Grissell",
        "filename": "The_Steamer_Great_Western_small.jpg"
    },
    "P1be701f": {
        "name": "Hansons Olefiant Gas Co",
        "filename": "The_Steamer_Great_Western_small.jpg"
    },
    "Pe384c5a": {
        "name": "Captain Harrison",
        "filename": "The_Steamer_Great_Western_small.jpg"
    },
    "P72c8bf9": {
        "name": "J. W. Harrison",
        "filename": "The_Steamer_Great_Western_small.jpg"
    },
    "Pd55260e": {
        "name": "George W. Hart",
        "filename": "The_Steamer_Great_Western_small.jpg"
    },
    "P5048c52": {
        "name": "John Hawkshaw",
        "filename": "The_Steamer_Great_Western_small.jpg"
    },
    "Pf908250": {
        "name": "George Hay",
        "filename": "The_Steamer_Great_Western_small.jpg"
    },
    "P3698a8b": {
        "name": "Phillip Hedger",
        "filename": "The_Steamer_Great_Western_small.jpg"
    },
    "P266a5c4": {
        "name": "George Heppelwhite",
        "filename": "The_Steamer_Great_Western_small.jpg"
    },
    "P55f6f1e": {
        "name": "Hepworth",
        "filename": "The_Steamer_Great_Western_small.jpg"
    },
    "P84127b3": {
        "name": "Mr. Heseltine",
        "filename": "The_Steamer_Great_Western_small.jpg"
    },
    "P8bb70d6": {
        "name": "John Lee Hevens",
        "filename": "The_Steamer_Great_Western_small.jpg"
    },
    "Pb5385ab": {
        "name": "C. A. Hohn",
        "filename": "The_Steamer_Great_Western_small.jpg"
    },
    "P638ceeb": {
        "name": "Thomas H. Holderness",
        "filename": "The_Steamer_Great_Western_small.jpg"
    },
    "P1b793ec": {
        "name": "F. H. Holmes",
        "filename": "The_Steamer_Great_Western_small.jpg"
    },
    "Pbd43e3a": {
        "name": "Henry T. Hope",
        "filename": "The_Steamer_Great_Western_small.jpg"
    },
    "P0fcf30e": {
        "name": "George H. Horsefall",
        "filename": "The_Steamer_Great_Western_small.jpg"
    },
    "Pdb5d414": {
        "name": "Mr. Horstman",
        "filename": "The_Steamer_Great_Western_small.jpg"
    },
    "P623ec00": {
        "name": "John A. P. How",
        "filename": "The_Steamer_Great_Western_small.jpg"
    },
    "Pd144fe2": {
        "name": "Thomas Howard",
        "filename": "The_Steamer_Great_Western_small.jpg"
    },
    "Pb0a4fd3": {
        "name": "Joseph Huddart",
        "filename": "The_Steamer_Great_Western_small.jpg"
    },
    "P7ef49dc": {
        "name": "Edward Humphreys",
        "filename": "The_Steamer_Great_Western_small.jpg"
    },
    "Pa49bee6": {
        "name": "John Cathart Hutchison",
        "filename": "The_Steamer_Great_Western_small.jpg"
    },
    "P2950435": {
        "name": "George Hutt",
        "filename": "The_Steamer_Great_Western_small.jpg"
    },
    "P6c17730": {
        "name": "George Inman",
        "filename": "The_Steamer_Great_Western_small.jpg"
    },
    "Pe36e2c8": {
        "name": "Richard Irvin",
        "filename": "The_Steamer_Great_Western_small.jpg"
    },
    "P4885d8e": {
        "name": "John S. Isaac",
        "filename": "The_Steamer_Great_Western_small.jpg"
    },
    "Pd89a707": {
        "name": "J Abbots Co",
        "filename": "The_Steamer_Great_Western_small.jpg"
    },
    "Pdc6a2d5": {
        "name": "Captain Charles Jackson",
        "filename": "The_Steamer_Great_Western_small.jpg"
    },
    "P40ae119": {
        "name": "William Jacomb",
        "filename": "The_Steamer_Great_Western_small.jpg"
    },
    "Pf0cde62": {
        "name": "James Watt Co",
        "filename": "The_Steamer_Great_Western_small.jpg"
    },
    "P2128985": {
        "name": "Reverend Septimus Jones",
        "filename": "The_Steamer_Great_Western_small.jpg"
    },
    "P6080bc1": {
        "name": "T. Jones",
        "filename": "The_Steamer_Great_Western_small.jpg"
    },
    "Pc539241": {
        "name": "John Kelk",
        "filename": "The_Steamer_Great_Western_small.jpg"
    },
    "Pd3e2109": {
        "name": "George D. Kittoe",
        "filename": "The_Steamer_Great_Western_small.jpg"
    },
    "Pc02ed9d": {
        "name": "John Laird",
        "filename": "The_Steamer_Great_Western_small.jpg"
    },
    "Pf24f828": {
        "name": "John Lalley",
        "filename": "The_Steamer_Great_Western_small.jpg"
    },
    "P480df59": {
        "name": "Thomas Lambert",
        "filename": "The_Steamer_Great_Western_small.jpg"
    },
    "Peeb254b": {
        "name": "J. Langden",
        "filename": "The_Steamer_Great_Western_small.jpg"
    },
    "P20a3db5": {
        "name": "W. Langdon",
        "filename": "The_Steamer_Great_Western_small.jpg"
    },
    "P82b6e13": {
        "name": "Mr. Langley",
        "filename": "The_Steamer_Great_Western_small.jpg"
    },
    "P8030440": {
        "name": "J. G. Lawrie",
        "filename": "The_Steamer_Great_Western_small.jpg"
    },
    "P90a5766": {
        "name": "J. M. Laws",
        "filename": "The_Steamer_Great_Western_small.jpg"
    },
    "Pffd94dc": {
        "name": "H. L. Leaf",
        "filename": "The_Steamer_Great_Western_small.jpg"
    },
    "P4d88cc3": {
        "name": "Thomas Ledger",
        "filename": "The_Steamer_Great_Western_small.jpg"
    },
    "P3fda980": {
        "name": "George W. Lenox",
        "filename": "The_Steamer_Great_Western_small.jpg"
    },
    "Peecf5e3": {
        "name": "Bradford C. Leslie",
        "filename": "The_Steamer_Great_Western_small.jpg"
    },
    "P9bf850e": {
        "name": "Henry Letherby",
        "filename": "The_Steamer_Great_Western_small.jpg"
    },
    "P8285385": {
        "name": "Mr. Lewis",
        "filename": "The_Steamer_Great_Western_small.jpg"
    },
    "P416753b": {
        "name": "Charles Lewsey",
        "filename": "The_Steamer_Great_Western_small.jpg"
    },
    "P12ffa7e": {
        "name": "H. Littledale",
        "filename": "The_Steamer_Great_Western_small.jpg"
    },
    "Pb70dc43": {
        "name": "Mr. Longley",
        "filename": "The_Steamer_Great_Western_small.jpg"
    },
    "Pb03c159": {
        "name": "Alfred Longsdon",
        "filename": "The_Steamer_Great_Western_small.jpg"
    },
    "P142bcd2": {
        "name": "Josiah Lorkin",
        "filename": "The_Steamer_Great_Western_small.jpg"
    },
    "P9aca42a": {
        "name": "Lowmoor Iron Co",
        "filename": "The_Steamer_Great_Western_small.jpg"
    },
    "P677040c": {
        "name": "Mr. Lucas",
        "filename": "The_Steamer_Great_Western_small.jpg"
    },
    "Peb032c4": {
        "name": "David MacIver",
        "filename": "The_Steamer_Great_Western_small.jpg"
    },
    "Pbce94a1": {
        "name": "William P. Maddison",
        "filename": "The_Steamer_Great_Western_small.jpg"
    },
    "P652223a": {
        "name": "Thomas E. Marsh",
        "filename": "The_Steamer_Great_Western_small.jpg"
    },
    "Pb3c3ca6": {
        "name": "William Martin",
        "filename": "The_Steamer_Great_Western_small.jpg"
    },
    "P53dbdb9": {
        "name": "R. I. Maryon",
        "filename": "The_Steamer_Great_Western_small.jpg"
    },
    "P71569ec": {
        "name": "Captain Bernard Matthews",
        "filename": "The_Steamer_Great_Western_small.jpg"
    },
    "Pe4b2989": {
        "name": "Charles May",
        "filename": "The_Steamer_Great_Western_small.jpg"
    },
    "Pb8282c0": {
        "name": "R. M. McCalmont",
        "filename": "The_Steamer_Great_Western_small.jpg"
    },
    "P90fc387": {
        "name": "William L. E. McLean",
        "filename": "The_Steamer_Great_Western_small.jpg"
    },
    "P9f64b02": {
        "name": "Alexander McLennan",
        "filename": "The_Steamer_Great_Western_small.jpg"
    },
    "P0ff36e8": {
        "name": "H. H. McMinnies",
        "filename": "The_Steamer_Great_Western_small.jpg"
    },
    "P930512e": {
        "name": "Philip J. W. Miles",
        "filename": "The_Steamer_Great_Western_small.jpg"
    },
    "P8e90c33": {
        "name": "Joseph Miller",
        "filename": "The_Steamer_Great_Western_small.jpg"
    },
    "Pabd5d24": {
        "name": "George Milner",
        "filename": "The_Steamer_Great_Western_small.jpg"
    },
    "P6abcb9c": {
        "name": "Stephen Moulton",
        "filename": "The_Steamer_Great_Western_small.jpg"
    },
    "P53cc2f2": {
        "name": "I. Natrass",
        "filename": "The_Steamer_Great_Western_small.jpg"
    },
    "P823fdd7": {
        "name": "John Neals",
        "filename": "The_Steamer_Great_Western_small.jpg"
    },
    "Pdbf58d8": {
        "name": "James B. Neilson",
        "filename": "The_Steamer_Great_Western_small.jpg"
    },
    "P2bd0b7f": {
        "name": "Mr. Nicholson",
        "filename": "The_Steamer_Great_Western_small.jpg"
    },
    "P6d89212": {
        "name": "Nielsons",
        "filename": "The_Steamer_Great_Western_small.jpg"
    },
    "P23e6766": {
        "name": "A. Normandy",
        "filename": "The_Steamer_Great_Western_small.jpg"
    },
    "P67cdecc": {
        "name": "Mr. Ogle",
        "filename": "The_Steamer_Great_Western_small.jpg"
    },
    "P8dd2ecb": {
        "name": "C. Osborne",
        "filename": "The_Steamer_Great_Western_small.jpg"
    },
    "Pf0b7125": {
        "name": "W. G. Owen",
        "filename": "The_Steamer_Great_Western_small.jpg"
    },
    "Pa9a7070": {
        "name": "Henry Parks",
        "filename": "The_Steamer_Great_Western_small.jpg"
    },
    "P5e30caf": {
        "name": "Patent Dessicating Co",
        "filename": "The_Steamer_Great_Western_small.jpg"
    },
    "P96e5946": {
        "name": "William Patterson",
        "filename": "The_Steamer_Great_Western_small.jpg"
    },
    "P7e4d7ac": {
        "name": "George Peacock",
        "filename": "The_Steamer_Great_Western_small.jpg"
    },
    "P939ed62": {
        "name": "John Penn",
        "filename": "The_Steamer_Great_Western_small.jpg"
    },
    "P7d2d7dd": {
        "name": "Francis Petit-Smith",
        "filename": "The_Steamer_Great_Western_small.jpg"
    },
    "Pf892fd7": {
        "name": "Richard Pilkington",
        "filename": "The_Steamer_Great_Western_small.jpg"
    },
    "P7a5da05": {
        "name": "Thomas Pollard",
        "filename": "The_Steamer_Great_Western_small.jpg"
    },
    "Pa2fe5cc": {
        "name": "Thomas Powell",
        "filename": "The_Steamer_Great_Western_small.jpg"
    },
    "P260486a": {
        "name": "J. J. Prideaux",
        "filename": "The_Steamer_Great_Western_small.jpg"
    },
    "P6c4267d": {
        "name": "C. Bayley Ransome",
        "filename": "The_Steamer_Great_Western_small.jpg"
    },
    "P6ec3c23": {
        "name": "C. J. Redpath",
        "filename": "The_Steamer_Great_Western_small.jpg"
    },
    "P19543f2": {
        "name": "A. H. Renton",
        "filename": "The_Steamer_Great_Western_small.jpg"
    },
    "P93a1dcf": {
        "name": "E. Ressig",
        "filename": "The_Steamer_Great_Western_small.jpg"
    },
    "P4b2a95b": {
        "name": "William Riddle",
        "filename": "The_Steamer_Great_Western_small.jpg"
    },
    "P1cccc5d": {
        "name": "Joshua Ridsdale",
        "filename": "The_Steamer_Great_Western_small.jpg"
    },
    "P13a58d2": {
        "name": "RIchard Roberts",
        "filename": "The_Steamer_Great_Western_small.jpg"
    },
    "P978fd90": {
        "name": "Albert Robinson",
        "filename": "The_Steamer_Great_Western_small.jpg"
    },
    "Pd61dfaf": {
        "name": "William Rodgers",
        "filename": "The_Steamer_Great_Western_small.jpg"
    },
    "P494c400": {
        "name": "Peter Rolls",
        "filename": "The_Steamer_Great_Western_small.jpg"
    },
    "P4da2997": {
        "name": "P. Rolt",
        "filename": "The_Steamer_Great_Western_small.jpg"
    },
    "P54b3b00": {
        "name": "W. G. Romaine",
        "filename": "The_Steamer_Great_Western_small.jpg"
    },
    "P6a05234": {
        "name": "Alexander M. Ross",
        "filename": "The_Steamer_Great_Western_small.jpg"
    },
    "P1cf5b1e": {
        "name": "Alexander S. Ross",
        "filename": "The_Steamer_Great_Western_small.jpg"
    },
    "P94cd78e": {
        "name": "William Rowett",
        "filename": "The_Steamer_Great_Western_small.jpg"
    },
    "Paacbced": {
        "name": "Rich Ruston",
        "filename": "The_Steamer_Great_Western_small.jpg"
    },
    "P8b9411f": {
        "name": "I. D. Samuda",
        "filename": "The_Steamer_Great_Western_small.jpg"
    },
    "P10c1fcc": {
        "name": "Nat Saunders",
        "filename": "The_Steamer_Great_Western_small.jpg"
    },
    "P7c23ee8": {
        "name": "S. M. Saxby",
        "filename": "The_Steamer_Great_Western_small.jpg"
    },
    "P0cabdc1": {
        "name": "William Schmollinger",
        "filename": "The_Steamer_Great_Western_small.jpg"
    },
    "Pb164b8a": {
        "name": "John Scott Russell",
        "filename": "The_Steamer_Great_Western_small.jpg"
    },
    "Pe024505": {
        "name": "Walter Shelley",
        "filename": "The_Steamer_Great_Western_small.jpg"
    },
    "P24031f8": {
        "name": "W. Shorter",
        "filename": "The_Steamer_Great_Western_small.jpg"
    },
    "Pc8f020a": {
        "name": "Charles Shrewdesrey",
        "filename": "The_Steamer_Great_Western_small.jpg"
    },
    "Pa394b15": {
        "name": "Thomas Silver",
        "filename": "The_Steamer_Great_Western_small.jpg"
    },
    "P5d2bbb3": {
        "name": "J. C. Sim",
        "filename": "The_Steamer_Great_Western_small.jpg"
    },
    "P41b5e96": {
        "name": "William Simms",
        "filename": "The_Steamer_Great_Western_small.jpg"
    },
    "P064a5a4": {
        "name": "James Simpson",
        "filename": "The_Steamer_Great_Western_small.jpg"
    },
    "Pbf60368": {
        "name": "F. W. Slade",
        "filename": "The_Steamer_Great_Western_small.jpg"
    },
    "P615b281": {
        "name": "C. Piazzi Smyth",
        "filename": "The_Steamer_Great_Western_small.jpg"
    },
    "P8aa9e45": {
        "name": "St Helens Ironworks",
        "filename": "The_Steamer_Great_Western_small.jpg"
    },
    "P0a5ba51": {
        "name": "Samuel Statham",
        "filename": "The_Steamer_Great_Western_small.jpg"
    },
    "P739a68f": {
        "name": "John Stobbs",
        "filename": "The_Steamer_Great_Western_small.jpg"
    },
    "P43314cc": {
        "name": "J. Stone",
        "filename": "The_Steamer_Great_Western_small.jpg"
    },
    "P4ec366b": {
        "name": "Christopher R. M. Talbot",
        "filename": "The_Steamer_Great_Western_small.jpg"
    },
    "P25981c7": {
        "name": "W. D. Taunton",
        "filename": "The_Steamer_Great_Western_small.jpg"
    },
    "Pb89d412": {
        "name": "John Taylor MA",
        "filename": "The_Steamer_Great_Western_small.jpg"
    },
    "P2a69982": {
        "name": "Thames Plate Glass Co",
        "filename": "The_Steamer_Great_Western_small.jpg"
    },
    "Pec5966c": {
        "name": "John Thompson",
        "filename": "The_Steamer_Great_Western_small.jpg"
    },
    "Pa4ca99c": {
        "name": "Robert Thomson",
        "filename": "The_Steamer_Great_Western_small.jpg"
    },
    "P85fd812": {
        "name": "John Trotman",
        "filename": "The_Steamer_Great_Western_small.jpg"
    },
    "Pd0d6b08": {
        "name": "Edwin Turner",
        "filename": "The_Steamer_Great_Western_small.jpg"
    },
    "Pe7f4f58": {
        "name": "Henry Turner",
        "filename": "The_Steamer_Great_Western_small.jpg"
    },
    "Pb963ffc": {
        "name": "Frederick Viney",
        "filename": "The_Steamer_Great_Western_small.jpg"
    },
    "P3ce3230": {
        "name": "Wainright Bros",
        "filename": "The_Steamer_Great_Western_small.jpg"
    },
    "P7af6539": {
        "name": "Wakefield",
        "filename": "The_Steamer_Great_Western_small.jpg"
    },
    "P80169ea": {
        "name": "H. Wakefield",
        "filename": "The_Steamer_Great_Western_small.jpg"
    },
    "P4ddec17": {
        "name": "Baldwin Walker",
        "filename": "The_Steamer_Great_Western_small.jpg"
    },
    "P6f059c6": {
        "name": "J. Walker",
        "filename": "The_Steamer_Great_Western_small.jpg"
    },
    "Pbee6b5c": {
        "name": "William Walker",
        "filename": "The_Steamer_Great_Western_small.jpg"
    },
    "P168e17b": {
        "name": "J. White",
        "filename": "The_Steamer_Great_Western_small.jpg"
    },
    "Pb87a041": {
        "name": "William White",
        "filename": "The_Steamer_Great_Western_small.jpg"
    },
    "P0ca02a4": {
        "name": "W. H. Whitehead",
        "filename": "The_Steamer_Great_Western_small.jpg"
    },
    "P9c29fbb": {
        "name": "F. Wilkins",
        "filename": "The_Steamer_Great_Western_small.jpg"
    },
    "Pcc393b0": {
        "name": "H. H. Williams",
        "filename": "The_Steamer_Great_Western_small.jpg"
    },
    "P2345e89": {
        "name": "R. Williams",
        "filename": "The_Steamer_Great_Western_small.jpg"
    },
    "Pfe19d4f": {
        "name": "Henry Wise",
        "filename": "The_Steamer_Great_Western_small.jpg"
    },
    "P831e63e": {
        "name": "Albert Wood",
        "filename": "The_Steamer_Great_Western_small.jpg"
    },
    "P0f01d1e": {
        "name": "Woods Bros",
        "filename": "The_Steamer_Great_Western_small.jpg"
    },
    "Pbd3f033": {
        "name": "G. J. Wright",
        "filename": "The_Steamer_Great_Western_small.jpg"
    },
    "Pfa9b1eb": {
        "name": "George Wyld MD",
        "filename": "The_Steamer_Great_Western_small.jpg"
    },
    "P700edd6": {
        "name": "John Yates",
        "filename": "The_Steamer_Great_Western_small.jpg"
    },
    "Bc631e2f": {
        "name": "Hoare & Barnetts",
        "filename": "The_Steamer_Great_Western_small.jpg"
    },
    "B0ca4b77": {
        "name": "Miles & Harford",
        "filename": "The_Steamer_Great_Western_small.jpg"
    },
    "B74447b8": {
        "name": "Osborne, Ward & Sons",
        "filename": "The_Steamer_Great_Western_small.jpg"
    },
    "Ba683a07": {
        "name": "Swain, Stevens & Co.",
        "filename": "The_Steamer_Great_Western_small.jpg"
    },
    "B19ef80d": {
        "name": "Seaward & Co.",
        "filename": "The_Steamer_Great_Western_small.jpg"
    },
    "B3d8b79b": {
        "name": "Armstrong & Coles",
        "filename": "The_Steamer_Great_Western_small.jpg"
    },
    "Bcfabe04": {
        "name": "Atchison & Hathaway",
        "filename": "The_Steamer_Great_Western_small.jpg"
    },
    "B4dc4a71": {
        "name": "Barnett & Moss",
        "filename": "The_Steamer_Great_Western_small.jpg"
    },
    "B6eff8f5": {
        "name": "Binks & Stephenson",
        "filename": "The_Steamer_Great_Western_small.jpg"
    },
    "B993da59": {
        "name": "Brown & Harfield",
        "filename": "The_Steamer_Great_Western_small.jpg"
    },
    "B344103c": {
        "name": "Brown Lennox & Co",
        "filename": "The_Steamer_Great_Western_small.jpg"
    },
    "Bfa1b8ed": {
        "name": "Brown Lenox & Co.",
        "filename": "The_Steamer_Great_Western_small.jpg"
    },
    "Be6cbb93": {
        "name": "Burbage & Healy",
        "filename": "The_Steamer_Great_Western_small.jpg"
    },
    "B29155a7": {
        "name": "C. Dowson & Sons",
        "filename": "The_Steamer_Great_Western_small.jpg"
    },
    "B9fa2583": {
        "name": "Catto & Miller",
        "filename": "The_Steamer_Great_Western_small.jpg"
    },
    "Bd548673": {
        "name": "Chance Bros & Co.",
        "filename": "The_Steamer_Great_Western_small.jpg"
    },
    "Bef1ef25": {
        "name": "Cundall & Howlett",
        "filename": "The_Steamer_Great_Western_small.jpg"
    },
    "B4a71df4": {
        "name": "Forbes, Forbes & Co.",
        "filename": "The_Steamer_Great_Western_small.jpg"
    },
    "B4bbbbef": {
        "name": "Fox Henderson & Co",
        "filename": "The_Steamer_Great_Western_small.jpg"
    },
    "B7a4d420": {
        "name": "Hartley & Co.",
        "filename": "The_Steamer_Great_Western_small.jpg"
    },
    "B219bbf8": {
        "name": "Harvey & Co",
        "filename": "The_Steamer_Great_Western_small.jpg"
    },
    "B3393e90": {
        "name": "Hawks & Crayshaw",
        "filename": "The_Steamer_Great_Western_small.jpg"
    },
    "B2965863": {
        "name": "Henry Wood & Co.",
        "filename": "The_Steamer_Great_Western_small.jpg"
    },
    "B792c63c": {
        "name": "Hingley & Co.",
        "filename": "The_Steamer_Great_Western_small.jpg"
    },
    "B05f55b5": {
        "name": "Hood & Cooper",
        "filename": "The_Steamer_Great_Western_small.jpg"
    },
    "B3aed46a": {
        "name": "Horsefell Mersey Steel & Iron Co.",
        "filename": "The_Steamer_Great_Western_small.jpg"
    },
    "B2184e19": {
        "name": "Howard & Ravenshill",
        "filename": "The_Steamer_Great_Western_small.jpg"
    },
    "Bceb5f2c": {
        "name": "Humphreys Tenant & Dyke",
        "filename": "The_Steamer_Great_Western_small.jpg"
    },
    "B6fee214": {
        "name": "J & M W. Ruthen",
        "filename": "The_Steamer_Great_Western_small.jpg"
    },
    "Be9ccbe8": {
        "name": "J & R Mitchison",
        "filename": "The_Steamer_Great_Western_small.jpg"
    },
    "B6377c4c": {
        "name": "J & White",
        "filename": "The_Steamer_Great_Western_small.jpg"
    },
    "Bb46b2dc": {
        "name": "J. S. Russell & Sons",
        "filename": "The_Steamer_Great_Western_small.jpg"
    },
    "B824baa0": {
        "name": "J. Taylor & Sons",
        "filename": "The_Steamer_Great_Western_small.jpg"
    },
    "Bc01559b": {
        "name": "J. Tylor & Sons",
        "filename": "The_Steamer_Great_Western_small.jpg"
    },
    "B13f2296": {
        "name": "J. W. Gray & Sons",
        "filename": "The_Steamer_Great_Western_small.jpg"
    },
    "B56483d2": {
        "name": "James & Nevill",
        "filename": "The_Steamer_Great_Western_small.jpg"
    },
    "Bd47fd98": {
        "name": "James Russell & Sons",
        "filename": "The_Steamer_Great_Western_small.jpg"
    },
    "B19ded1e": {
        "name": "John & Robert White",
        "filename": "The_Steamer_Great_Western_small.jpg"
    },
    "B2caf67b": {
        "name": "John Bourne & Co. Greenock",
        "filename": "The_Steamer_Great_Western_small.jpg"
    },
    "B33fac3c": {
        "name": "John Gray & Son",
        "filename": "The_Steamer_Great_Western_small.jpg"
    },
    "B4d7b4d3": {
        "name": "Martin & Co",
        "filename": "The_Steamer_Great_Western_small.jpg"
    },
    "B52e8120": {
        "name": "Miller & Ravenhill",
        "filename": "The_Steamer_Great_Western_small.jpg"
    },
    "B3aad15b": {
        "name": "Milne & Son",
        "filename": "The_Steamer_Great_Western_small.jpg"
    },
    "Bed4c81c": {
        "name": "Money, Wigram & Co.",
        "filename": "The_Steamer_Great_Western_small.jpg"
    },
    "B6bf4b6f": {
        "name": "Nixon & Co.",
        "filename": "The_Steamer_Great_Western_small.jpg"
    },
    "B09136d1": {
        "name": "Noah Stringley & Sons",
        "filename": "The_Steamer_Great_Western_small.jpg"
    },
    "Bd9ad45c": {
        "name": "Patent Wood & Fibrous Slab Co.",
        "filename": "The_Steamer_Great_Western_small.jpg"
    },
    "Bd6e8039": {
        "name": "Petit & Co.",
        "filename": "The_Steamer_Great_Western_small.jpg"
    },
    "B87f9b8e": {
        "name": "Peto, Brassey, Betts & Co.",
        "filename": "The_Steamer_Great_Western_small.jpg"
    },
    "B368913e": {
        "name": "R. J. Newall & Co.",
        "filename": "The_Steamer_Great_Western_small.jpg"
    },
    "B82e726b": {
        "name": "Redpath & Leigh",
        "filename": "The_Steamer_Great_Western_small.jpg"
    },
    "Bd09b958": {
        "name": "S. Beale & Co",
        "filename": "The_Steamer_Great_Western_small.jpg"
    },
    "Bd4d1e52": {
        "name": "Sims & Muntz",
        "filename": "The_Steamer_Great_Western_small.jpg"
    },
    "B817509e": {
        "name": "Smith & Philips",
        "filename": "The_Steamer_Great_Western_small.jpg"
    },
    "Bbdace09": {
        "name": "T & W Forester",
        "filename": "The_Steamer_Great_Western_small.jpg"
    },
    "B7f628fc": {
        "name": "Thames Ironworks & Shipbuilding Co.",
        "filename": "The_Steamer_Great_Western_small.jpg"
    },
    "B7ff6c30": {
        "name": "Troughton & Bevan",
        "filename": "The_Steamer_Great_Western_small.jpg"
    },
    "B955b19a": {
        "name": "W. Morgan & Son",
        "filename": "The_Steamer_Great_Western_small.jpg"
    },
    "B3d912e1": {
        "name": "Watkins & Hill",
        "filename": "The_Steamer_Great_Western_small.jpg"
    },
    "B283f31f": {
        "name": "Wilkins & Weatherly",
        "filename": "The_Steamer_Great_Western_small.jpg"
    },
    "B02b0a04": {
        "name": "William Day & Co.",
        "filename": "The_Steamer_Great_Western_small.jpg"
    },
    "B3ac7435": {
        "name": "William Kuper & Co./Glass Elliott & Co.",
        "filename": "The_Steamer_Great_Western_small.jpg"
    }
}